locate_pixelcolor_cupy/README.md
locate_pixelcolor_cupy/__init__.py
locate_pixelcolor_cupy/requirements.txt
locate_pixelcolor_cupy/thirdparty.json
locate_pixelcolor_cupy-0.11.dist-info/LICENSE.rst
locate_pixelcolor_cupy-0.11.dist-info/METADATA
locate_pixelcolor_cupy-0.11.dist-info/WHEEL
locate_pixelcolor_cupy-0.11.dist-info/top_level.txt
locate_pixelcolor_cupy-0.11.dist-info/RECORD
