Metadata-Version: 2.1
Name: locate-pixelcolor-cupy
Version: 0.11
Summary: Detects colors in images up to 8 times as fast as NumPy
Home-page: https://github.com/hansalemaos/locate_pixelcolor_cupy
Author: Johannes Fischer
Author-email: aulasparticularesdealemaosp@gmail.com
License: MIT
Keywords: Cupy,image,search,rgb
Classifier: Development Status :: 4 - Beta
Classifier: Programming Language :: Python :: 3 :: Only
Classifier: Programming Language :: Python :: 3.10
Classifier: Topic :: Software Development :: Libraries :: Python Modules
Classifier: Topic :: Utilities
License-File: LICENSE.rst
Requires-Dist: cupy
Requires-Dist: numpy
